valteci/__init__.py
valteci/valteci_junior.py
valteci-0.0.1.dist-info/METADATA
valteci-0.0.1.dist-info/WHEEL
valteci-0.0.1.dist-info/licenses/LICENSE
valteci-0.0.1.dist-info/RECORD
